{
    "agent_id": 120,
    "gender": "F",
    "final_status": "Dead",
    "marital_regime": "None",
    "cause_of_death": "Starvation / Exhaustion",
    "year_of_death": 12,
    "final_savings": -16.93,
    "history": [
        {
            "year": 1,
            "age": 18,
            "location_sector": "Africa",
            "energy": 90,
            "savings_bank_balance": 119.88,
            "social_class": "Middle",
            "marital_regime": "None"
        },
        {
            "year": 2,
            "age": 19,
            "location_sector": "Africa",
            "energy": 80,
            "savings_bank_balance": 81.59,
            "social_class": "Middle",
            "marital_regime": "None"
        },
        {
            "year": 3,
            "age": 20,
            "location_sector": "Africa",
            "energy": 70,
            "savings_bank_balance": 86.47,
            "social_class": "Middle",
            "marital_regime": "None"
        },
        {
            "year": 4,
            "age": 21,
            "location_sector": "Asia",
            "energy": 45,
            "savings_bank_balance": 12.35,
            "social_class": "Poor",
            "marital_regime": "None"
        },
        {
            "year": 5,
            "age": 22,
            "location_sector": "Asia",
            "energy": 70,
            "savings_bank_balance": 1.03,
            "social_class": "Poor",
            "marital_regime": "None"
        },
        {
            "year": 6,
            "age": 23,
            "location_sector": "Europe",
            "energy": 45,
            "savings_bank_balance": 2.91,
            "social_class": "Poor",
            "marital_regime": "None"
        },
        {
            "year": 7,
            "age": 24,
            "location_sector": "Europe",
            "energy": 35,
            "savings_bank_balance": 3.59,
            "social_class": "Poor",
            "marital_regime": "None"
        },
        {
            "year": 8,
            "age": 25,
            "location_sector": "Europe",
            "energy": 25,
            "savings_bank_balance": 3.07,
            "social_class": "Poor",
            "marital_regime": "None"
        },
        {
            "year": 9,
            "age": 26,
            "location_sector": "Europe",
            "energy": 19,
            "savings_bank_balance": -0.93,
            "social_class": "Poor",
            "marital_regime": "None"
        },
        {
            "year": 10,
            "age": 27,
            "location_sector": "Europe",
            "energy": 13,
            "savings_bank_balance": -4.93,
            "social_class": "Poor",
            "marital_regime": "None"
        },
        {
            "year": 11,
            "age": 28,
            "location_sector": "Europe",
            "energy": 7,
            "savings_bank_balance": -8.93,
            "social_class": "Poor",
            "marital_regime": "None"
        },
        {
            "year": 12,
            "age": 29,
            "location_sector": "Europe",
            "energy": 1,
            "savings_bank_balance": -12.93,
            "social_class": "Poor",
            "marital_regime": "None"
        }
    ]
}