{
    "agent_id": 73,
    "gender": "M",
    "final_status": "Dead",
    "marital_regime": "None",
    "cause_of_death": "Starvation / Exhaustion",
    "year_of_death": 12,
    "final_savings": -14.15,
    "history": [
        {
            "year": 1,
            "age": 18,
            "location_sector": "Asia",
            "energy": 90,
            "savings_bank_balance": 91.74,
            "social_class": "Middle",
            "marital_regime": "None"
        },
        {
            "year": 2,
            "age": 19,
            "location_sector": "Asia",
            "energy": 80,
            "savings_bank_balance": 62.2,
            "social_class": "Middle",
            "marital_regime": "None"
        },
        {
            "year": 3,
            "age": 20,
            "location_sector": "Asia",
            "energy": 70,
            "savings_bank_balance": 54.58,
            "social_class": "Middle",
            "marital_regime": "Separate"
        },
        {
            "year": 4,
            "age": 21,
            "location_sector": "Africa",
            "energy": 45,
            "savings_bank_balance": 43.96,
            "social_class": "Middle",
            "marital_regime": "Separate"
        },
        {
            "year": 5,
            "age": 22,
            "location_sector": "Africa",
            "energy": 70,
            "savings_bank_balance": 2.01,
            "social_class": "Poor",
            "marital_regime": "Separate"
        },
        {
            "year": 6,
            "age": 23,
            "location_sector": "Africa",
            "energy": 60,
            "savings_bank_balance": 5.69,
            "social_class": "Poor",
            "marital_regime": "Separate"
        },
        {
            "year": 7,
            "age": 24,
            "location_sector": "Europe",
            "energy": 35,
            "savings_bank_balance": 6.37,
            "social_class": "Poor",
            "marital_regime": "Separate"
        },
        {
            "year": 8,
            "age": 25,
            "location_sector": "Europe",
            "energy": 25,
            "savings_bank_balance": 5.85,
            "social_class": "Poor",
            "marital_regime": "Separate"
        },
        {
            "year": 9,
            "age": 26,
            "location_sector": "Europe",
            "energy": 19,
            "savings_bank_balance": 1.85,
            "social_class": "Poor",
            "marital_regime": "Separate"
        },
        {
            "year": 9,
            "event": "\ud83d\udc94 Neural separation triggered. Left Agent 58."
        },
        {
            "year": 10,
            "age": 27,
            "location_sector": "Europe",
            "energy": 13,
            "savings_bank_balance": -2.15,
            "social_class": "Poor",
            "marital_regime": "None"
        },
        {
            "year": 11,
            "age": 28,
            "location_sector": "Europe",
            "energy": 7,
            "savings_bank_balance": -6.15,
            "social_class": "Poor",
            "marital_regime": "Separate"
        },
        {
            "year": 12,
            "age": 29,
            "location_sector": "Europe",
            "energy": 1,
            "savings_bank_balance": -10.15,
            "social_class": "Poor",
            "marital_regime": "Separate"
        },
        {
            "year": 12,
            "event": "\ud83d\udc94 Neural separation triggered. Left Agent 24."
        }
    ]
}