{
    "agent_id": 123,
    "assigned_gender": "F",
    "total_kids_count": 0,
    "children_produced_ids": [],
    "final_status": "Alive",
    "cause_of_death": "N/A",
    "year_of_death": "N/A",
    "final_savings_balance": 487.18,
    "final_energy_level": 90,
    "travel_history_log": [
        "Asia"
    ],
    "biometric_history_log": [
        {
            "year": 2,
            "age": 1,
            "location_sector": "Asia",
            "energy": 90,
            "savings_bank_balance": 82.18,
            "social_class": "Middle"
        },
        {
            "year": 3,
            "age": 2,
            "location_sector": "Asia",
            "energy": 90,
            "savings_bank_balance": 52.18,
            "social_class": "Middle"
        },
        {
            "year": 4,
            "age": 3,
            "location_sector": "Asia",
            "energy": 90,
            "savings_bank_balance": 82.18,
            "social_class": "Middle"
        },
        {
            "year": 5,
            "age": 4,
            "location_sector": "Asia",
            "energy": 90,
            "savings_bank_balance": 112.18,
            "social_class": "Middle"
        },
        {
            "year": 6,
            "age": 5,
            "location_sector": "Asia",
            "energy": 90,
            "savings_bank_balance": 102.18,
            "social_class": "Middle"
        },
        {
            "year": 7,
            "age": 6,
            "location_sector": "Asia",
            "energy": 90,
            "savings_bank_balance": 132.18,
            "social_class": "Wealthy"
        },
        {
            "year": 8,
            "age": 7,
            "location_sector": "Asia",
            "energy": 90,
            "savings_bank_balance": 147.18,
            "social_class": "Wealthy"
        },
        {
            "year": 9,
            "age": 8,
            "location_sector": "Asia",
            "energy": 90,
            "savings_bank_balance": 177.18,
            "social_class": "Wealthy"
        },
        {
            "year": 10,
            "age": 9,
            "location_sector": "Asia",
            "energy": 90,
            "savings_bank_balance": 167.18,
            "social_class": "Wealthy"
        },
        {
            "year": 11,
            "age": 10,
            "location_sector": "Asia",
            "energy": 90,
            "savings_bank_balance": 197.18,
            "social_class": "Wealthy"
        },
        {
            "year": 12,
            "age": 11,
            "location_sector": "Asia",
            "energy": 90,
            "savings_bank_balance": 187.18,
            "social_class": "Wealthy"
        },
        {
            "year": 13,
            "age": 12,
            "location_sector": "Asia",
            "energy": 90,
            "savings_bank_balance": 202.18,
            "social_class": "Wealthy"
        },
        {
            "year": 14,
            "age": 13,
            "location_sector": "Asia",
            "energy": 90,
            "savings_bank_balance": 217.18,
            "social_class": "Wealthy"
        },
        {
            "year": 15,
            "age": 14,
            "location_sector": "Asia",
            "energy": 90,
            "savings_bank_balance": 207.18,
            "social_class": "Wealthy"
        },
        {
            "year": 16,
            "age": 15,
            "location_sector": "Asia",
            "energy": 90,
            "savings_bank_balance": 222.18,
            "social_class": "Wealthy"
        },
        {
            "year": 17,
            "age": 16,
            "location_sector": "Asia",
            "energy": 90,
            "savings_bank_balance": 237.18,
            "social_class": "Wealthy"
        },
        {
            "year": 18,
            "age": 17,
            "location_sector": "Asia",
            "energy": 90,
            "savings_bank_balance": 267.18,
            "social_class": "Wealthy"
        },
        {
            "year": 19,
            "age": 18,
            "location_sector": "Asia",
            "energy": 90,
            "savings_bank_balance": 257.18,
            "social_class": "Wealthy"
        },
        {
            "year": 20,
            "age": 19,
            "location_sector": "Asia",
            "energy": 90,
            "savings_bank_balance": 272.18,
            "social_class": "Wealthy"
        },
        {
            "year": 21,
            "age": 20,
            "location_sector": "Asia",
            "energy": 90,
            "savings_bank_balance": 287.18,
            "social_class": "Wealthy"
        },
        {
            "year": 22,
            "age": 21,
            "location_sector": "Asia",
            "energy": 90,
            "savings_bank_balance": 277.18,
            "social_class": "Wealthy"
        },
        {
            "year": 23,
            "age": 22,
            "location_sector": "Asia",
            "energy": 90,
            "savings_bank_balance": 307.18,
            "social_class": "Wealthy"
        },
        {
            "year": 24,
            "age": 23,
            "location_sector": "Asia",
            "energy": 90,
            "savings_bank_balance": 337.18,
            "social_class": "Wealthy"
        },
        {
            "year": 25,
            "age": 24,
            "location_sector": "Asia",
            "energy": 90,
            "savings_bank_balance": 367.18,
            "social_class": "Wealthy"
        },
        {
            "year": 26,
            "age": 25,
            "location_sector": "Asia",
            "energy": 90,
            "savings_bank_balance": 397.18,
            "social_class": "Wealthy"
        },
        {
            "year": 27,
            "age": 26,
            "location_sector": "Asia",
            "energy": 90,
            "savings_bank_balance": 412.18,
            "social_class": "Wealthy"
        },
        {
            "year": 28,
            "age": 27,
            "location_sector": "Asia",
            "energy": 90,
            "savings_bank_balance": 427.18,
            "social_class": "Wealthy"
        },
        {
            "year": 29,
            "age": 28,
            "location_sector": "Asia",
            "energy": 90,
            "savings_bank_balance": 457.18,
            "social_class": "Wealthy"
        },
        {
            "year": 30,
            "age": 29,
            "location_sector": "Asia",
            "energy": 90,
            "savings_bank_balance": 487.18,
            "social_class": "Wealthy"
        }
    ],
    "marriage_history": [
        {
            "year": 15,
            "partner_id": 80,
            "partner_class": "Middle",
            "outcome": "Courtship Rejected (Brain Output: 0.4)"
        },
        {
            "year": 15,
            "partner_id": 125,
            "partner_class": "Wealthy",
            "outcome": "Courtship Rejected (Brain Output: 0.39)"
        },
        {
            "year": 15,
            "partner_id": 6,
            "partner_class": "Middle",
            "outcome": "Courtship Rejected (Brain Output: 0.41)"
        },
        {
            "year": 15,
            "partner_id": 121,
            "partner_class": "Wealthy",
            "outcome": "Courtship Rejected (Brain Output: 0.4)"
        },
        {
            "year": 16,
            "partner_id": 6,
            "partner_class": "Middle",
            "outcome": "Courtship Rejected (Brain Output: 0.39)"
        },
        {
            "year": 16,
            "partner_id": 125,
            "partner_class": "Wealthy",
            "outcome": "Courtship Rejected (Brain Output: 0.38)"
        },
        {
            "year": 16,
            "partner_id": 2,
            "partner_class": "Middle",
            "outcome": "Courtship Rejected (Brain Output: 0.39)"
        },
        {
            "year": 16,
            "partner_id": 121,
            "partner_class": "Wealthy",
            "outcome": "Courtship Rejected (Brain Output: 0.38)"
        },
        {
            "year": 17,
            "partner_id": 140,
            "partner_class": "Wealthy",
            "outcome": "Courtship Rejected (Brain Output: 0.36)"
        },
        {
            "year": 17,
            "partner_id": 2,
            "partner_class": "Middle",
            "outcome": "Courtship Rejected (Brain Output: 0.37)"
        },
        {
            "year": 17,
            "partner_id": 125,
            "partner_class": "Wealthy",
            "outcome": "Courtship Rejected (Brain Output: 0.36)"
        },
        {
            "year": 18,
            "partner_id": 2,
            "partner_class": "Middle",
            "outcome": "Courtship Rejected (Brain Output: 0.34)"
        },
        {
            "year": 18,
            "partner_id": 125,
            "partner_class": "Wealthy",
            "outcome": "Courtship Rejected (Brain Output: 0.33)"
        },
        {
            "year": 18,
            "partner_id": 152,
            "partner_class": "Wealthy",
            "outcome": "Courtship Rejected (Brain Output: 0.33)"
        },
        {
            "year": 19,
            "partner_id": 125,
            "partner_class": "Wealthy",
            "outcome": "Courtship Rejected (Brain Output: 0.35)"
        },
        {
            "year": 19,
            "partner_id": 2,
            "partner_class": "Wealthy",
            "outcome": "Courtship Rejected (Brain Output: 0.35)"
        },
        {
            "year": 19,
            "partner_id": 155,
            "partner_class": "Wealthy",
            "outcome": "Courtship Rejected (Brain Output: 0.35)"
        },
        {
            "year": 20,
            "partner_id": 163,
            "partner_class": "Wealthy",
            "outcome": "Courtship Rejected (Brain Output: 0.34)"
        },
        {
            "year": 20,
            "partner_id": 152,
            "partner_class": "Wealthy",
            "outcome": "Courtship Rejected (Brain Output: 0.34)"
        },
        {
            "year": 21,
            "partner_id": 125,
            "partner_class": "Wealthy",
            "outcome": "Courtship Rejected (Brain Output: 0.33)"
        },
        {
            "year": 21,
            "partner_id": 163,
            "partner_class": "Wealthy",
            "outcome": "Courtship Rejected (Brain Output: 0.33)"
        },
        {
            "year": 22,
            "partner_id": 173,
            "partner_class": "Wealthy",
            "outcome": "Courtship Rejected (Brain Output: 0.34)"
        },
        {
            "year": 23,
            "partner_id": 140,
            "partner_class": "Wealthy",
            "outcome": "Courtship Rejected (Brain Output: 0.33)"
        },
        {
            "year": 23,
            "partner_id": 163,
            "partner_class": "Wealthy",
            "outcome": "Courtship Rejected (Brain Output: 0.33)"
        },
        {
            "year": 23,
            "partner_id": 175,
            "partner_class": "Wealthy",
            "outcome": "Courtship Rejected (Brain Output: 0.33)"
        },
        {
            "year": 24,
            "partner_id": 182,
            "partner_class": "Wealthy",
            "outcome": "Courtship Rejected (Brain Output: 0.31)"
        },
        {
            "year": 24,
            "partner_id": 172,
            "partner_class": "Wealthy",
            "outcome": "Courtship Rejected (Brain Output: 0.31)"
        },
        {
            "year": 24,
            "partner_id": 121,
            "partner_class": "Middle",
            "outcome": "Courtship Rejected (Brain Output: 0.32)"
        },
        {
            "year": 25,
            "partner_id": 175,
            "partner_class": "Wealthy",
            "outcome": "Courtship Rejected (Brain Output: 0.28)"
        },
        {
            "year": 25,
            "partner_id": 121,
            "partner_class": "Middle",
            "outcome": "Courtship Rejected (Brain Output: 0.29)"
        },
        {
            "year": 25,
            "partner_id": 166,
            "partner_class": "Wealthy",
            "outcome": "Courtship Rejected (Brain Output: 0.28)"
        },
        {
            "year": 25,
            "partner_id": 188,
            "partner_class": "Middle",
            "outcome": "Courtship Rejected (Brain Output: 0.29)"
        },
        {
            "year": 27,
            "partner_id": 152,
            "partner_class": "Middle",
            "outcome": "Courtship Rejected (Brain Output: 0.25)"
        },
        {
            "year": 27,
            "partner_id": 187,
            "partner_class": "Wealthy",
            "outcome": "Courtship Rejected (Brain Output: 0.25)"
        },
        {
            "year": 27,
            "partner_id": 182,
            "partner_class": "Wealthy",
            "outcome": "Courtship Rejected (Brain Output: 0.25)"
        },
        {
            "year": 28,
            "partner_id": 172,
            "partner_class": "Wealthy",
            "outcome": "Courtship Rejected (Brain Output: 0.23)"
        },
        {
            "year": 29,
            "partner_id": 187,
            "partner_class": "Wealthy",
            "outcome": "Courtship Rejected (Brain Output: 0.21)"
        },
        {
            "year": 29,
            "partner_id": 173,
            "partner_class": "Wealthy",
            "outcome": "Courtship Rejected (Brain Output: 0.21)"
        },
        {
            "year": 29,
            "partner_id": 184,
            "partner_class": "Wealthy",
            "outcome": "Courtship Rejected (Brain Output: 0.21)"
        },
        {
            "year": 29,
            "partner_id": 182,
            "partner_class": "Wealthy",
            "outcome": "Courtship Rejected (Brain Output: 0.21)"
        },
        {
            "year": 30,
            "partner_id": 187,
            "partner_class": "Wealthy",
            "outcome": "Courtship Rejected (Brain Output: 0.19)"
        },
        {
            "year": 30,
            "partner_id": 163,
            "partner_class": "Wealthy",
            "outcome": "Courtship Rejected (Brain Output: 0.19)"
        },
        {
            "year": 30,
            "partner_id": 140,
            "partner_class": "Wealthy",
            "outcome": "Courtship Rejected (Brain Output: 0.19)"
        },
        {
            "year": 30,
            "partner_id": 184,
            "partner_class": "Wealthy",
            "outcome": "Courtship Rejected (Brain Output: 0.19)"
        },
        {
            "year": 30,
            "partner_id": 175,
            "partner_class": "Wealthy",
            "outcome": "Courtship Rejected (Brain Output: 0.19)"
        }
    ],
    "brain_weights": [
        -0.6177678206157103,
        -0.3996576062572802,
        2.3088346206068353,
        0.17608876700143952,
        -0.1505223162794802
    ]
}