{
    "agent_id": 227,
    "assigned_gender": "F",
    "total_kids_count": 0,
    "children_produced_ids": [],
    "final_status": "Alive",
    "cause_of_death": "N/A",
    "year_of_death": "N/A",
    "final_savings_balance": 172.14,
    "final_energy_level": 90,
    "travel_history_log": [
        "Asia"
    ],
    "biometric_history_log": [
        {
            "year": 24,
            "age": 1,
            "location_sector": "Asia",
            "energy": 90,
            "savings_bank_balance": 77.14,
            "social_class": "Wealthy"
        },
        {
            "year": 25,
            "age": 2,
            "location_sector": "Asia",
            "energy": 90,
            "savings_bank_balance": 92.14,
            "social_class": "Wealthy"
        },
        {
            "year": 26,
            "age": 3,
            "location_sector": "Asia",
            "energy": 90,
            "savings_bank_balance": 122.14,
            "social_class": "Wealthy"
        },
        {
            "year": 27,
            "age": 4,
            "location_sector": "Asia",
            "energy": 90,
            "savings_bank_balance": 152.14,
            "social_class": "Wealthy"
        },
        {
            "year": 28,
            "age": 5,
            "location_sector": "Asia",
            "energy": 90,
            "savings_bank_balance": 167.14,
            "social_class": "Wealthy"
        },
        {
            "year": 29,
            "age": 6,
            "location_sector": "Asia",
            "energy": 90,
            "savings_bank_balance": 182.14,
            "social_class": "Wealthy"
        },
        {
            "year": 30,
            "age": 7,
            "location_sector": "Asia",
            "energy": 90,
            "savings_bank_balance": 172.14,
            "social_class": "Wealthy"
        }
    ],
    "marriage_history": [],
    "brain_weights": [
        -0.6257137290879958,
        0.060779731399678225,
        1.553599707079377,
        0.201013564059845,
        -0.07924279593717234
    ]
}